hyalus/__init__.py
hyalus/metadata.json
hyalus/py.typed
hyalus/assertions/__init__.py
hyalus/assertions/apply.py
hyalus/assertions/compare.py
hyalus/config/__init__.py
hyalus/config/common.py
hyalus/config/loader.py
hyalus/config/steps/__init__.py
hyalus/config/steps/assertions.py
hyalus/config/steps/base.py
hyalus/config/steps/run.py
hyalus/config/tags/__init__.py
hyalus/config/tags/base.py
hyalus/config/tags/runtime.py
hyalus/config/tags/types.py
hyalus/parse/__init__.py
hyalus/parse/base.py
hyalus/parse/csv.py
hyalus/parse/factory.py
hyalus/parse/h5.py
hyalus/parse/json.py
hyalus/parse/tsv.py
hyalus/run/__init__.py
hyalus/run/clean.py
hyalus/run/common.py
hyalus/run/list.py
hyalus/run/python.py
hyalus/run/runsuite.py
hyalus/run/runtest.py
hyalus/run/settings.py
hyalus/run/template.py
hyalus/run/static/config_template
hyalus/settings/.gitfood
hyalus/utils/__init__.py
hyalus/utils/file_utils.py
hyalus/utils/json_utils.py
hyalus/utils/logging_utils.py
hyalus/utils/pandas_utils.py
hyalus/utils/typing_utils.py
hyalus-0.1.1.data/scripts/hyalus
hyalus-0.1.1.dist-info/LICENSE
hyalus-0.1.1.dist-info/METADATA
hyalus-0.1.1.dist-info/WHEEL
hyalus-0.1.1.dist-info/entry_points.txt
hyalus-0.1.1.dist-info/top_level.txt
hyalus-0.1.1.dist-info/RECORD
