Metadata-Version: 2.1
Name: hyalus
Version: 0.1.1
Summary: Test harness and utilities for Sequencing Health software testing
Author: David McConnell
Author-email: david.mcconnell@sequencinghealth.com
Maintainer: David McConnell
Maintainer-email: david.mcconnell@sequencinghealth.com
Classifier: Programming Language :: Python
Classifier: Programming Language :: Python :: 3
Classifier: Programming Language :: Python :: 3.10
Classifier: Programming Language :: Python :: 3.11
Classifier: Operating System :: OS Independent
License-File: LICENSE
Requires-Dist: typing-extensions
